entangle_matrix/__init__.py
entangle_matrix/client.py
entangle_matrix/exceptions.py
entangle_matrix/models.py
entangle_matrix/utils.py
entangle_matrix-0.2.0.dist-info/licenses/LICENSE
tests/__init__.py
tests/test_client.py
entangle_matrix-0.2.0.dist-info/METADATA
entangle_matrix-0.2.0.dist-info/WHEEL
entangle_matrix-0.2.0.dist-info/top_level.txt
entangle_matrix-0.2.0.dist-info/RECORD
