Metadata-Version: 2.4
Name: entangle-matrix
Version: 0.2.0
Summary: Python SDK for Entangle Matrix API - Create and manage AI-powered digital twins
Home-page: https://github.com/qbit-codes/entangle-python-client
Author: QBit Codes
Author-email: QBit Codes <hello@qbitcodes.com>
License: MIT
Project-URL: Homepage, https://github.com/qbit-codes/entangle-python-client
Project-URL: Documentation, https://github.com/qbit-codes/entangle-python-client#readme
Project-URL: Repository, https://github.com/qbit-codes/entangle-python-client
Project-URL: Bug Tracker, https://github.com/qbit-codes/entangle-python-client/issues
Keywords: matrix,api,sdk,chat,messaging,digital-twin,ai
Classifier: Development Status :: 3 - Alpha
Classifier: Intended Audience :: Developers
Classifier: License :: OSI Approved :: MIT License
Classifier: Operating System :: OS Independent
Classifier: Programming Language :: Python :: 3
Classifier: Programming Language :: Python :: 3.9
Classifier: Programming Language :: Python :: 3.10
Classifier: Programming Language :: Python :: 3.11
Classifier: Programming Language :: Python :: 3.12
Classifier: Topic :: Communications :: Chat
Classifier: Topic :: Internet :: WWW/HTTP :: HTTP Servers
Classifier: Topic :: Software Development :: Libraries :: Python Modules
Requires-Python: >=3.9
License-File: LICENSE
Requires-Dist: aiohttp>=3.8.0
Requires-Dist: aiofiles>=23.2.1
Provides-Extra: dev
Requires-Dist: pytest>=7.4.0; extra == "dev"
Requires-Dist: pytest-asyncio>=0.21.0; extra == "dev"
Requires-Dist: pytest-cov>=4.1.0; extra == "dev"
Requires-Dist: black>=23.0.0; extra == "dev"
Requires-Dist: isort>=5.12.0; extra == "dev"
Requires-Dist: flake8>=6.0.0; extra == "dev"
Requires-Dist: mypy>=1.5.0; extra == "dev"
Dynamic: author
Dynamic: home-page
Dynamic: license-file
Dynamic: requires-python
